ORBIT/__init__.py
ORBIT/config.py
ORBIT/manager.py
ORBIT/parametric.py
ORBIT/supply_chain.py
ORBIT/core/__init__.py
ORBIT/core/cargo.py
ORBIT/core/components.py
ORBIT/core/environment.py
ORBIT/core/exceptions.py
ORBIT/core/library.py
ORBIT/core/port.py
ORBIT/core/supply_chain.py
ORBIT/core/vessel.py
ORBIT/core/defaults/__init__.py
ORBIT/core/defaults/common_costs.yaml
ORBIT/core/defaults/costs_by_procurement_year.csv
ORBIT/core/defaults/process_times.yaml
ORBIT/core/logic/__init__.py
ORBIT/core/logic/vessel_logic.py
ORBIT/phases/__init__.py
ORBIT/phases/base.py
ORBIT/phases/design/__init__.py
ORBIT/phases/design/_cables.py
ORBIT/phases/design/array_system_design.py
ORBIT/phases/design/design_phase.py
ORBIT/phases/design/electrical_export.py
ORBIT/phases/design/export_system_design.py
ORBIT/phases/design/monopile_design.py
ORBIT/phases/design/mooring_system_design.py
ORBIT/phases/design/oss_design.py
ORBIT/phases/design/oss_design_floating.py
ORBIT/phases/design/scour_protection_design.py
ORBIT/phases/design/semi_submersible_design.py
ORBIT/phases/design/spar_design.py
ORBIT/phases/install/__init__.py
ORBIT/phases/install/install_phase.py
ORBIT/phases/install/cable_install/__init__.py
ORBIT/phases/install/cable_install/array.py
ORBIT/phases/install/cable_install/common.py
ORBIT/phases/install/cable_install/export.py
ORBIT/phases/install/jacket_install/__init__.py
ORBIT/phases/install/jacket_install/common.py
ORBIT/phases/install/jacket_install/standard.py
ORBIT/phases/install/monopile_install/__init__.py
ORBIT/phases/install/monopile_install/common.py
ORBIT/phases/install/monopile_install/standard.py
ORBIT/phases/install/mooring_install/__init__.py
ORBIT/phases/install/mooring_install/mooring.py
ORBIT/phases/install/oss_install/__init__.py
ORBIT/phases/install/oss_install/common.py
ORBIT/phases/install/oss_install/floating.py
ORBIT/phases/install/oss_install/standard.py
ORBIT/phases/install/quayside_assembly_tow/__init__.py
orbit_nrel-1.2.5.dist-info/licenses/LICENSE
orbit_nrel-1.2.5.dist-info/METADATA
orbit_nrel-1.2.5.dist-info/WHEEL
orbit_nrel-1.2.5.dist-info/top_level.txt
orbit_nrel-1.2.5.dist-info/RECORD
