Metadata-Version: 2.4
Name: orbit-nrel
Version: 1.2.5
Summary: Offshore Renewables Balance of system and Installation Tool
Author-email: Nick Riccobono <nicholas.riccobono@nrel.gov>, Rob Hammond <rob.hammond@nrel.gov>, Jake Nunemaker <jacob.nunemaker@nrel.gov>
License:    Copyright (c) 2020 Alliance for Sustainable Energy, LLC
Project-URL: source, https://github.com/WISDEM/ORBIT
Project-URL: documentation, https://wisdem.github.io/ORBIT/
Project-URL: issues, https://github.com/WISDEM/ORBIT/issues
Project-URL: changelog, https://github.com/WISDEM/ORBIT/blob/main/docs/source/changelog.rst
Keywords: python3,wind-energy,balance-of-system,wind-installation,discrete-event-simulation,simulation
Classifier: Development Status :: 4 - Beta
Classifier: Intended Audience :: Developers
Classifier: Intended Audience :: Science/Research
Classifier: Intended Audience :: Other Audience
Classifier: License :: OSI Approved :: Apache Software License
Classifier: Natural Language :: English
Classifier: Operating System :: OS Independent
Classifier: Programming Language :: Python
Classifier: Programming Language :: Python :: 3 :: Only
Classifier: Programming Language :: Python :: 3.10
Classifier: Programming Language :: Python :: 3.11
Classifier: Programming Language :: Python :: 3.12
Classifier: Programming Language :: Python :: 3.13
Classifier: Programming Language :: Python :: 3.14
Classifier: Topic :: Scientific/Engineering
Classifier: Topic :: Software Development :: Libraries :: Python Modules
Requires-Python: >3.9
License-File: LICENSE
Requires-Dist: numpy
Requires-Dist: simpy
Requires-Dist: marmot-agents>=0.2.5
Requires-Dist: scipy
Requires-Dist: pandas
Requires-Dist: pyyaml
Requires-Dist: python-benedict
Requires-Dist: statsmodels
Provides-Extra: dev
Requires-Dist: pre-commit; extra == "dev"
Requires-Dist: black; extra == "dev"
Requires-Dist: isort; extra == "dev"
Requires-Dist: pytest; extra == "dev"
Requires-Dist: pytest-cov; extra == "dev"
Requires-Dist: sphinx; extra == "dev"
Requires-Dist: sphinx-rtd-theme; extra == "dev"
Requires-Dist: ruff; extra == "dev"
Provides-Extra: plot
Requires-Dist: matplotlib; extra == "plot"
Dynamic: license-file
